docs/api.rst
docs/index.rst
docs/init_msa.rst
docs/io.rst
docs/language_model.rst
docs/training.rst
docs/visualization.rst
learnMSA/__init__.py
learnMSA/_version.py
learnMSA/docs/api.rst
learnMSA/docs/index.rst
learnMSA/docs/init_msa.rst
learnMSA/docs/io.rst
learnMSA/docs/language_model.rst
learnMSA/docs/training.rst
learnMSA/docs/visualization.rst
learnMSA/msa_hmm/Align.py
learnMSA/msa_hmm/AlignInsertions.py
learnMSA/msa_hmm/AlignmentModel.py
learnMSA/msa_hmm/AncProbsLayer.py
learnMSA/msa_hmm/Bidirectional.py
learnMSA/msa_hmm/Configuration.py
learnMSA/msa_hmm/ConvertPriors.py
learnMSA/msa_hmm/DirichletMixture.py
learnMSA/msa_hmm/Emitter.py
learnMSA/msa_hmm/Initializers.py
learnMSA/msa_hmm/MSA2HMM.py
learnMSA/msa_hmm/MsaHmmCell.py
learnMSA/msa_hmm/MsaHmmLayer.py
learnMSA/msa_hmm/Priors.py
learnMSA/msa_hmm/SequenceDataset.py
learnMSA/msa_hmm/TotalProbabilityCell.py
learnMSA/msa_hmm/Training.py
learnMSA/msa_hmm/Transitioner.py
learnMSA/msa_hmm/Utility.py
learnMSA/msa_hmm/Visualize.py
learnMSA/msa_hmm/Viterbi.py
learnMSA/msa_hmm/__init__.py
learnMSA/msa_hmm/trained_prior/128_True_float32__dirichlet.h5
learnMSA/msa_hmm/trained_prior/128_True_float64__dirichlet.h5
learnMSA/msa_hmm/trained_prior/1_True_float32__dirichlet.h5
learnMSA/msa_hmm/trained_prior/1_True_float64__dirichlet.h5
learnMSA/msa_hmm/trained_prior/256_True_float32__dirichlet.h5
learnMSA/msa_hmm/trained_prior/256_True_float64__dirichlet.h5
learnMSA/msa_hmm/trained_prior/32_True_float32__dirichlet.h5
learnMSA/msa_hmm/trained_prior/32_True_float64__dirichlet.h5
learnMSA/msa_hmm/trained_prior/3_True_float32__dirichlet.h5
learnMSA/msa_hmm/trained_prior/3_True_float64__dirichlet.h5
learnMSA/msa_hmm/trained_prior/64_True_float32__dirichlet.h5
learnMSA/msa_hmm/trained_prior/64_True_float64__dirichlet.h5
learnMSA/msa_hmm/trained_prior/9_True_float32__dirichlet.h5
learnMSA/msa_hmm/trained_prior/9_True_float64__dirichlet.h5
learnMSA/msa_hmm/trained_prior/emissions.log
learnmsa-2.0.16.dist-info/METADATA
learnmsa-2.0.16.dist-info/WHEEL
learnmsa-2.0.16.dist-info/entry_points.txt
learnmsa-2.0.16.dist-info/top_level.txt
learnmsa-2.0.16.dist-info/RECORD
