Metadata-Version: 2.4
Name: learnMSA
Version: 2.0.16
Summary: learnMSA: Learning and Aligning large Protein Families
Home-page: https://github.com/Gaius-Augustus/learnMSA
Author: Felix Becker
Author-email: beckerfelix94@gmail.com
License: MIT
Requires-Dist: tensorflow[and-cuda]==2.19
Requires-Dist: networkx
Requires-Dist: logomaker
Requires-Dist: seaborn
Requires-Dist: biopython>=1.69
Requires-Dist: pyfamsa
Requires-Dist: transformers
Requires-Dist: imageio
Requires-Dist: tf-keras==2.19
Requires-Dist: SentencePiece
Dynamic: author
Dynamic: author-email
Dynamic: home-page
Dynamic: license
Dynamic: requires-dist
Dynamic: summary
